fm_track-1.0.0.dist-info/METADATA
fm_track-1.0.0.dist-info/RECORD
fm_track-1.0.0.dist-info/WHEEL
fm_track-1.0.0.dist-info/top_level.txt
fmtrack/__init__.py
fmtrack/el_papers.mplstyle
fmtrack/input_info.py
fmtrack/post_process.py
fmtrack/pre_process.py
fmtrack/run_tracking_all_steps.py
fmtrack/tracking.py
