Metadata-Version: 2.1
Name: fm-track
Version: 1.0.0
Summary: Feature-based fiducial marker tracking software for applications in cell mechanics
Home-page: https://github.com/elejeune11/FM-Track
Author: Emma Marie Lejeune
Author-email: emma.lejeune.11@gmail.com
License: MIT
Keywords: fiducial marker cell mechanics tracking feature
Platform: UNKNOWN
Classifier: Development Status :: 3 - Alpha
Classifier: License :: OSI Approved :: MIT License
Classifier: Programming Language :: Python :: 3.6
Classifier: Topic :: Scientific/Engineering :: Bio-Informatics
Classifier: Intended Audience :: Science/Research
Requires-Python: >=3.0, <=3.6
Requires-Dist: markdown
Requires-Dist: numpy
Requires-Dist: matplotlib
Requires-Dist: scipy
Requires-Dist: sklearn-contrib-py-earth
Requires-Dist: scikit-image
Requires-Dist: scikit-learn
